test_buffer/__init__.py
test_buffer/test_buffer.py
time_series_buffer/__init__.py
time_series_buffer/buffer.py
time_series_buffer-0.1.4b0.dist-info/LICENSE
time_series_buffer-0.1.4b0.dist-info/METADATA
time_series_buffer-0.1.4b0.dist-info/WHEEL
time_series_buffer-0.1.4b0.dist-info/top_level.txt
time_series_buffer-0.1.4b0.dist-info/RECORD
