Metadata-Version: 2.1
Name: time-series-buffer
Version: 0.1.4b0
Summary: This package provides support for buffering time-series with uncertainty.
Home-page: https://github.com/PTB-PSt1/time-series-buffer
Author: Maximilian Gruber, Björn Ludwig
Author-email: maximilian.gruber@ptb.de
License: UNKNOWN
Keywords: buffer time-series uncertainty metrology
Platform: UNKNOWN
Classifier: Topic :: Utilities
Classifier: Topic :: Scientific/Engineering
Classifier: Topic :: Software Development :: Libraries :: Python Modules
Classifier: Intended Audience :: Education
Classifier: Intended Audience :: Science/Research
Classifier: License :: OSI Approved :: GNU Lesser General Public License v3 or later (LGPLv3+)
Classifier: Programming Language :: Python :: 3
Classifier: Operating System :: OS Independent
Requires-Python: >=3.5
Requires-Dist: numpy
Requires-Dist: uncertainties
